ratchada_processor
