Metadata-Version: 2.1
Name: ratchada-util
Version: 0.2.0
Summary: A Python lib/util for Ratchada Whisper model
Home-page: https://github.com/tm-zoon-patcharawiwatpong/ratchada_util
Author: tm-zoon
Author-email: zoon_p@thinkingmachin.es
License: MIT
Keywords: RATCAHA-WHISPER
Classifier: Programming Language :: Python :: 3.10
Classifier: Programming Language :: Python :: 3.11
Classifier: License :: OSI Approved :: MIT License
Classifier: Operating System :: OS Independent
License-File: LICENSE
Requires-Dist: regex==2023.10.3; python_version >= "3.10" and python_version < "3.12"
Requires-Dist: more-itertools==10.1.0; python_version >= "3.10" and python_version < "3.12"
